README.md
setup.py
django_auto_static_libs/__init__.py
django_auto_static_libs/apps.py
django_auto_static_libs/libraries.py
django_auto_static_libs/models.py
django_auto_static_libs/settings.py
django_auto_static_libs.egg-info/PKG-INFO
django_auto_static_libs.egg-info/SOURCES.txt
django_auto_static_libs.egg-info/dependency_links.txt
django_auto_static_libs.egg-info/requires.txt
django_auto_static_libs.egg-info/top_level.txt
django_auto_static_libs/management/__init__.py
django_auto_static_libs/management/commands/__init__.py
django_auto_static_libs/management/commands/static-libs-download.py
django_auto_static_libs/providers/BaseProvider.py
django_auto_static_libs/providers/GithubProvider.py
django_auto_static_libs/providers/__init__.py